unicode_charnames/DerivedName.txt
unicode_charnames/__init__.py
unicode_charnames/_unicode_names.py
unicode_charnames/_version.py
unicode_charnames/charnames.py
unicode_charnames-16.0.0.dist-info/LICENSE
unicode_charnames-16.0.0.dist-info/METADATA
unicode_charnames-16.0.0.dist-info/WHEEL
unicode_charnames-16.0.0.dist-info/top_level.txt
unicode_charnames-16.0.0.dist-info/RECORD
