Metadata-Version: 2.1
Name: unicode_charnames
Version: 16.0.0
Summary: Look up Unicode character name or code point label and search in Unicode character names.
Home-page: https://github.com/mlodewijck/unicode_charnames
Author: Marc Lodewijck
Author-email: mlodewijck@gmail.com
License: MIT
Project-URL: Bug Reports, https://github.com/mlodewijck/unicode_charnames/issues
Project-URL: Source, https://github.com/mlodewijck/unicode_charnames/
Keywords: Unicode,Unicode data,Unicode characters,character names,characters
Classifier: Intended Audience :: Developers
Classifier: License :: OSI Approved :: MIT License
Classifier: Programming Language :: Python :: 3.8
Classifier: Programming Language :: Python :: 3.9
Classifier: Programming Language :: Python :: 3.10
Classifier: Programming Language :: Python :: 3.11
Classifier: Programming Language :: Python :: 3.12
Classifier: Topic :: Text Processing :: Filters
Classifier: Topic :: Utilities
Requires-Python: >=3.8
License-File: LICENSE
